iewil/__init__.py
iewil/cli.py
iewil/functions/__init__.py
iewil/functions/captcha.py
iewil/functions/datastore.py
iewil/functions/display.py
iewil/functions/free.py
iewil/functions/htmlscrap.py
iewil/functions/show_error.py
iewil-0.0.8.dist-info/licenses/LICENSE
iewil-0.0.8.dist-info/METADATA
iewil-0.0.8.dist-info/WHEEL
iewil-0.0.8.dist-info/entry_points.txt
iewil-0.0.8.dist-info/top_level.txt
iewil-0.0.8.dist-info/RECORD
