Metadata-Version: 2.4
Name: iewil
Version: 0.0.8
Summary: Modul pribadi iewil: display, captcha, html scraping, cache storage
Author: iewilmaestro
Author-email: purna.iera@gmail.com
Keywords: iewil,display,captcha,scraping,cache
Classifier: Development Status :: 1 - Planning
Classifier: Intended Audience :: Developers
Classifier: Programming Language :: Python :: 3
Classifier: Operating System :: OS Independent
License-File: LICENSE
Requires-Dist: requests
Requires-Dist: pillow
Dynamic: author
Dynamic: author-email
Dynamic: classifier
Dynamic: description
Dynamic: description-content-type
Dynamic: keywords
Dynamic: license-file
Dynamic: requires-dist
Dynamic: summary
